Workbook

Sheet Revenue Build
A1: DCF Model — Revenue Build ($mm)
A2: Line Item | B2: FY2020 ◄ Historical | C2: FY2021 | D2: FY2022 | E2: FY2023 | F2: FY2024 ◄ Forecast | G2: FY2025 | H2: FY2026 | I2: FY2027 | J2: FY2028
A4: SEGMENT A — Core Products
A5: Revenue ($mm) | F5: =E5*(1+F6) | G5: =F5*(1+G6) | H5: =G5*(1+H6) | I5: =H5*(1+I6) | J5: =I5*(1+J6)
A6: YoY Growth Rate
A8: SEGMENT B — Adjacent Markets
A9: Revenue ($mm) | F9: =E9*(1+F10) | G9: =F9*(1+G10) | H9: =G9*(1+H10) | I9: =H9*(1+I10) | J9: =I9*(1+J10)
A10: YoY Growth Rate
A12: SEGMENT C — Emerging / New
A13: Revenue ($mm) | F13: =E13*(1+F14) | G13: =F13*(1+G14) | H13: =G13*(1+H14) | I13: =H13*(1+I14) | J13: =I13*(1+J14)
A14: YoY Growth Rate
A16: Total Revenue ($mm) | B16: =B5+B9+B13 | C16: =C5+C9+C13 | D16: =D5+D9+D13 | E16: =E5+E9+E13 | F16: =F5+F9+F13 | G16: =G5+G9+G13 | H16: =H5+H9+H13 | I16: =I5+I9+I13 | J16: =J5+J9+J13
A17: Total Revenue Growth % | B17: =0 | C17: =IFERROR(C16/B16-1,0) | D17: =IFERROR(D16/C16-1,0) | E17: =IFERROR(E16/D16-1,0) | F17: =IFERROR(F16/E16-1,0) | G17: =IFERROR(G16/F16-1,0) | H17: =IFERROR(H16/G16-1,0) | I17: =IFERROR(I16/H16-1,0) | J17: =IFERROR(J16/I16-1,0)

Sheet P&L Projections
A1: DCF Model — P&L Projections ($mm)
A2: Line Item | B2: FY2020 | C2: FY2021 | D2: FY2022 | E2: FY2023 | F2: FY2024 | G2: FY2025 | H2: FY2026 | I2: FY2027 | J2: FY2028
A4: Revenue | B4: ='Revenue Build'!B16 | C4: ='Revenue Build'!C16 | D4: ='Revenue Build'!D16 | E4: ='Revenue Build'!E16 | F4: ='Revenue Build'!F16 | G4: ='Revenue Build'!G16 | H4: ='Revenue Build'!H16 | I4: ='Revenue Build'!I16 | J4: ='Revenue Build'!J16
A5: Revenue Growth % | B5: =0 | C5: =IFERROR(C4/B4-1,0) | D5: =IFERROR(D4/C4-1,0) | E5: =IFERROR(E4/D4-1,0) | F5: =IFERROR(F4/E4-1,0) | G5: =IFERROR(G4/F4-1,0) | H5: =IFERROR(H4/G4-1,0) | I5: =IFERROR(I4/H4-1,0) | J5: =IFERROR(J4/I4-1,0)
A6: Cost of Goods Sold | B6: =B4*B7 | C6: =C4*C7 | D6: =D4*D7 | E6: =E4*E7 | F6: =F4*F7 | G6: =G4*G7 | H6: =H4*H7 | I6: =I4*I7 | J6: =J4*J7
A7: COGS % of Revenue
A8: Gross Profit | B8: =B4-B6 | C8: =C4-C6 | D8: =D4-D6 | E8: =E4-E6 | F8: =F4-F6 | G8: =G4-G6 | H8: =H4-H6 | I8: =I4-I6 | J8: =J4-J6
A9: Gross Margin % | B9: =IFERROR(B8/B4,0) | C9: =IFERROR(C8/C4,0) | D9: =IFERROR(D8/D4,0) | E9: =IFERROR(E8/E4,0) | F9: =IFERROR(F8/F4,0) | G9: =IFERROR(G8/G4,0) | H9: =IFERROR(H8/H4,0) | I9: =IFERROR(I8/I4,0) | J9: =IFERROR(J8/J4,0)
A11: Selling, General & Administrative | B11: =B4*B12 | C11: =C4*C12 | D11: =D4*D12 | E11: =E4*E12 | F11: =F4*F12 | G11: =G4*G12 | H11: =H4*H12 | I11: =I4*I12 | J11: =J4*J12
A12: SG&A % of Revenue
A13: Research & Development | B13: =B4*B14 | C13: =C4*C14 | D13: =D4*D14 | E13: =E4*E14 | F13: =F4*F14 | G13: =G4*G14 | H13: =H4*H14 | I13: =I4*I14 | J13: =J4*J14
A14: R&D % of Revenue
A16: EBITDA | B16: =B8-B11-B13 | C16: =C8-C11-C13 | D16: =D8-D11-D13 | E16: =E8-E11-E13 | F16: =F8-F11-F13 | G16: =G8-G11-G13 | H16: =H8-H11-H13 | I16: =I8-I11-I13 | J16: =J8-J11-J13
A17: EBITDA Margin % | B17: =IFERROR(B16/B4,0) | C17: =IFERROR(C16/C4,0) | D17: =IFERROR(D16/D4,0) | E17: =IFERROR(E16/E4,0) | F17: =IFERROR(F16/F4,0) | G17: =IFERROR(G16/G4,0) | H17: =IFERROR(H16/H4,0) | I17: =IFERROR(I16/I4,0) | J17: =IFERROR(J16/J4,0)
A19: Depreciation & Amortization
A20: EBIT (Operating Income) | B20: =B16-B19 | C20: =C16-C19 | D20: =D16-D19 | E20: =E16-E19 | F20: =F16-F19 | G20: =G16-G19 | H20: =H16-H19 | I20: =I16-I19 | J20: =J16-J19
A21: EBIT Margin % | B21: =IFERROR(B20/B4,0) | C21: =IFERROR(C20/C4,0) | D21: =IFERROR(D20/D4,0) | E21: =IFERROR(E20/E4,0) | F21: =IFERROR(F20/F4,0) | G21: =IFERROR(G20/G4,0) | H21: =IFERROR(H20/H4,0) | I21: =IFERROR(I20/I4,0) | J21: =IFERROR(J20/J4,0)
A23: Interest Expense (Net)
A24: Earnings Before Tax | B24: =B20-B23 | C24: =C20-C23 | D24: =D20-D23 | E24: =E20-E23 | F24: =F20-F23 | G24: =G20-G23 | H24: =H20-H23 | I24: =I20-I23 | J24: =J20-J23
A25: Effective Tax Rate
A26: Income Tax Expense | B26: =MAX(B24*B25,0) | C26: =MAX(C24*C25,0) | D26: =MAX(D24*D25,0) | E26: =MAX(E24*E25,0) | F26: =MAX(F24*F25,0) | G26: =MAX(G24*G25,0) | H26: =MAX(H24*H25,0) | I26: =MAX(I24*I25,0) | J26: =MAX(J24*J25,0)
A27: Net Income | B27: =B24-B26 | C27: =C24-C26 | D27: =D24-D26 | E27: =E24-E26 | F27: =F24-F26 | G27: =G24-G26 | H27: =H24-H26 | I27: =I24-I26 | J27: =J24-J26
A28: Net Margin % | B28: =IFERROR(B27/B4,0) | C28: =IFERROR(C27/C4,0) | D28: =IFERROR(D27/D4,0) | E28: =IFERROR(E27/E4,0) | F28: =IFERROR(F27/F4,0) | G28: =IFERROR(G27/G4,0) | H28: =IFERROR(H27/H4,0) | I28: =IFERROR(I27/I4,0) | J28: =IFERROR(J27/J4,0)

Sheet Free Cash Flow
A1: DCF Model — Unlevered Free Cash Flow ($mm)
A2: Line Item | F2: FY2024 | G2: FY2025 | H2: FY2026 | I2: FY2027 | J2: FY2028
A4: EBIT (Operating Income) | F4: ='P&L Projections'!F20 | G4: ='P&L Projections'!G20 | H4: ='P&L Projections'!H20 | I4: ='P&L Projections'!I20 | J4: ='P&L Projections'!J20
A5: Less: Taxes on EBIT (Tax Rate) | F5: ='P&L Projections'!F25 | G5: ='P&L Projections'!G25 | H5: ='P&L Projections'!H25 | I5: ='P&L Projections'!I25 | J5: ='P&L Projections'!J25
A6: Net Operating Profit After Tax (NOPAT) | F6: =F4*(1-F5) | G6: =G4*(1-G5) | H6: =H4*(1-H5) | I6: =I4*(1-I5) | J6: =J4*(1-J5)
A8: Add: Depreciation & Amortization | F8: ='P&L Projections'!F19 | G8: ='P&L Projections'!G19 | H8: ='P&L Projections'!H19 | I8: ='P&L Projections'!I19 | J8: ='P&L Projections'!J19
A9: Less: Capital Expenditures (Capex)
A10: Less: Increase in Net Working Capital
A12: Unlevered Free Cash Flow (UFCF) | F12: =F6+F8-F9-F10 | G12: =G6+G8-G9-G10 | H12: =H6+H8-H9-H10 | I12: =I6+I8-I9-I10 | J12: =J6+J8-J9-J10
A14: Discount Period (Mid-Year Convention) | F14: =0.5 | G14: =1.5 | H14: =2.5 | I14: =3.5 | J14: =4.5
A15: WACC | F15: ='WACC Calculation'!B19 | G15: ='WACC Calculation'!B19 | H15: ='WACC Calculation'!B19 | I15: ='WACC Calculation'!B19 | J15: ='WACC Calculation'!B19
A16: Discount Factor | F16: =1/(1+F15)^F14 | G16: =1/(1+G15)^G14 | H16: =1/(1+H15)^H14 | I16: =1/(1+I15)^I14 | J16: =1/(1+J15)^J14
A17: PV of Free Cash Flow | F17: =F12*F16 | G17: =G12*G16 | H17: =H12*H16 | I17: =I12*I16 | J17: =J12*J16
A19: Sum of PV of FCFs (=NPV) | F19: =SUM(F17:J17)

Sheet WACC Calculation
A1: DCF Model — WACC Calculation
A3: COST OF EQUITY (CAPM)
A4: Risk-Free Rate (10-yr UST)
A5: Equity Risk Premium (ERP)
A6: Levered Beta
A7: Cost of Equity [Ke] | B7: =B4+B6*B5
A9: COST OF DEBT
A10: Pre-Tax Cost of Debt
A11: Marginal Tax Rate
A12: After-Tax Cost of Debt [Kd] | B12: =B10*(1-B11)
A14: CAPITAL STRUCTURE
A15: Equity Weight [We]
A16: Debt Weight [Wd] | B16: =1-B15
A18: WACC (BLENDED RATE)
A19: WACC | B19: =B7*B15+B12*B16
A21: SIZE & SPECIFIC RISK PREMIA
A22: Size Premium
A23: Company-Specific Risk Premium
A24: Adjusted Cost of Equity | B24: =B7+B22+B23

Sheet Terminal Value
A1: DCF Model — Terminal Value Analysis
A2: Line Item | B2: Value
A4: GORDON GROWTH MODEL (Perpetuity Growth)
A5: Terminal Year UFCF ($mm) | B5: ='Free Cash Flow'!J12
A6: Terminal Growth Rate (g)
A7: WACC | B7: ='WACC Calculation'!B19
A8: Terminal Value (GGM) | B8: =IFERROR(B5*(1+B6)/(B7-B6),0)
A9: Discount Factor (end of Year 5) | B9: =IFERROR(1/(1+B7)^5,0)
A10: PV of Terminal Value (GGM) ($mm) | B10: =B8*B9
A12: EXIT MULTIPLE METHOD
A13: Terminal Year EBITDA ($mm) | B13: ='P&L Projections'!J16
A14: Exit EV / EBITDA Multiple
A15: Terminal Value (EV/EBITDA) | B15: =B13*B14
A16: PV of Terminal Value (EV/EBITDA) ($mm) | B16: =B15*B9
A18: SELECTED TERMINAL VALUE
A19: Selected TV Method (GGM shown) | B19: =B8
A20: PV of Selected Terminal Value ($mm) | B20: =B10

Sheet Valuation Summary
A1: DCF Model — Valuation Summary ($mm)
A2: All values in $mm unless noted. Blue = input, Green = cross-sheet, Black = formula.
A4: DCF ENTERPRISE VALUE
A5: Sum of PV of Free Cash Flows ($mm) | B5: =SUM('Free Cash Flow'!F17:'Free Cash Flow'!J17)
A6: PV of Terminal Value ($mm) | B6: ='Terminal Value'!B20
A7: Enterprise Value (EV) ($mm) | B7: =B5+B6
A8: Less: Net Debt (Debt – Cash) ($mm)
A9: Equity Value ($mm) | B9: =B7-B8
A10: Diluted Shares Outstanding (mm)
A11: Implied Share Price ($) | B11: =IFERROR(B9/B10,0)
A13: VALUATION RANGE SUMMARY
A14: Bull Case — Higher Exit Multiple / Growth
A15: Base Case — Selected TV (above) | B15: =B7
A16: Bear Case — Lower Exit Multiple / Growth
A18: XIRR / IMPLIED YIELD ANALYSIS
A19: Dates (Dec 31 of each year) — for XIRR formula
A20: Year 0 Date (Investment Date)
A21: Year 1 Date
A22: Year 2 Date
A23: Year 3 Date
A24: Year 4 Date
A25: Year 5 Date (Exit Date)
A27: Yr 0 Cash Flow — Initial Investment | B27: =-B7
A28: Yr 1 Cash Flow — UFCF Year 1 | B28: ='Free Cash Flow'!F12
A29: Yr 2 Cash Flow — UFCF Year 2 | B29: ='Free Cash Flow'!G12
A30: Yr 3 Cash Flow — UFCF Year 3 | B30: ='Free Cash Flow'!H12
A31: Yr 4 Cash Flow — UFCF Year 4 | B31: ='Free Cash Flow'!I12
A32: Yr 5 Cash Flow — UFCF + TV | B32: ='Free Cash Flow'!J12+'Terminal Value'!B19
A34: XIRR (Implied Yield on FCFs + TV) | B34: =IFERROR(XIRR(B27:B32,B20:B25),0)
