Workbook

Sheet Revenue Build
A1: Line Item | B1: FY2020 | C1: FY2021 | D1: FY2022 | E1: FY2023 | F1: FY2024 | G1: FY2025
A2: Segment A Revenue
A3: Segment A Growth
A4: Segment B Revenue
A5: Segment B Growth
A6: Total Revenue | B6: =B2+B4 | C6: =C2+C4 | D6: =D2+D4 | E6: =E2+E4 | F6: =F2+F4 | G6: =G2+G4

Sheet Income Statement
A1: Line Item | B1: FY2020 | C1: FY2021 | D1: FY2022 | E1: FY2023 | F1: FY2024 | G1: FY2025
A2: Revenue | B2: ='Revenue Build'!B6 | C2: ='Revenue Build'!C6 | D2: ='Revenue Build'!D6 | E2: ='Revenue Build'!E6 | F2: ='Revenue Build'!F6 | G2: ='Revenue Build'!G6
A3: COGS
A4: Gross Profit | B4: =B2-B3 | C4: =C2-C3 | D4: =D2-D3 | E4: =E2-E3 | F4: =F2-F3 | G4: =G2-G3
A5: SG&A
A6: EBITDA | B6: =B4-B5 | C6: =C4-C5 | D6: =D4-D5 | E6: =E4-E5 | F6: =F4-F5 | G6: =G4-G5
A7: D&A
A8: EBIT | B8: =B6-B7 | C8: =C6-C7 | D8: =D6-D7 | E8: =E6-E7 | F8: =F6-F7 | G8: =G6-G7
A9: Tax
A10: Net Income | B10: =B8-B9 | C10: =C8-C9 | D10: =D8-D9 | E10: =E8-E9 | F10: =F8-F9 | G10: =G8-G9

Sheet Free Cash Flow
A1: Line Item | B1: FY2020 | C1: FY2021 | D1: FY2022 | E1: FY2023 | F1: FY2024 | G1: FY2025
A2: EBITDA | B2: ='Income Statement'!B6 | C2: ='Income Statement'!C6 | D2: ='Income Statement'!D6 | E2: ='Income Statement'!E6 | F2: ='Income Statement'!F6 | G2: ='Income Statement'!G6
A3: Tax
A4: D&A | B4: ='Income Statement'!B7 | C4: ='Income Statement'!C7 | D4: ='Income Statement'!D7 | E4: ='Income Statement'!E7 | F4: ='Income Statement'!F7 | G4: ='Income Statement'!G7
A5: Changes in Working Capital
A6: CapEx
A7: Unlevered FCF | B7: =B2-B3+B4+B5-B6 | C7: =C2-C3+C4+C5-C6 | D7: =D2-D3+D4+D5-D6 | E7: =E2-E3+E4+E5-E6 | F7: =F2-F3+F4+F5-F6 | G7: =G2-G3+G4+G5-G6

Sheet DCF Valuation
A1: Metric | B1: Value
A2: WACC
A3: Terminal Growth Rate
A4: Terminal Value
A5: PV of FCFs
A6: Enterprise Value | B6: =B4+B5
