Workbook

Sheet Income Statement
A1: Line Item | B1: FY2020 | C1: FY2021 | D1: FY2022 | E1: FY2023 | F1: FY2024 | G1: FY2025
A2: Revenue
A3: COGS
A4: Gross Profit | B4: =B2-B3 | C4: =C2-C3 | D4: =D2-D3 | E4: =E2-E3 | F4: =F2-F3 | G4: =G2-G3
A5: SG&A
A6: EBITDA | B6: =B4-B5 | C6: =C4-C5 | D6: =D4-D5 | E6: =E4-E5 | F6: =F4-F5 | G6: =G4-G5
A7: D&A
A8: EBIT | B8: =B6-B7 | C8: =C6-C7 | D8: =D6-D7 | E8: =E6-E7 | F8: =F6-F7 | G8: =G6-G7
A9: Interest Expense | B9: ='Debt Schedule'!B16 | C9: ='Debt Schedule'!C16 | D9: ='Debt Schedule'!D16 | E9: ='Debt Schedule'!E16 | F9: ='Debt Schedule'!F16 | G9: ='Debt Schedule'!G16
A10: EBT | B10: =B8-B9 | C10: =C8-C9 | D10: =D8-D9 | E10: =E8-E9 | F10: =F8-F9 | G10: =G8-G9
A11: Tax
A12: Net Income | B12: =B10-B11 | C12: =C10-C11 | D12: =D10-D11 | E12: =E10-E11 | F12: =F10-F11 | G12: =G10-G11

Sheet Balance Sheet
A1: Line Item | B1: FY2020 | C1: FY2021 | D1: FY2022 | E1: FY2023 | F1: FY2024 | G1: FY2025
A2: Cash
A3: Accounts Receivable
A4: Inventory
A5: Other Current Assets
A6: Total Current Assets | B6: =SUM(B2:B5) | C6: =SUM(C2:C5) | D6: =SUM(D2:D5) | E6: =SUM(E2:E5) | F6: =SUM(F2:F5) | G6: =SUM(G2:G5)
A7: PP&E Net
A8: Goodwill
A9: Other Non-Current Assets
A10: Total Assets | B10: =B6+B7+B8+B9 | C10: =C6+C7+C8+C9 | D10: =D6+D7+D8+D9 | E10: =E6+E7+E8+E9 | F10: =F6+F7+F8+F9 | G10: =G6+G7+G8+G9
A11: Accounts Payable
A12: Accrued Expenses
A13: Current Portion of Debt
A14: Total Current Liabilities | B14: =SUM(B11:B13) | C14: =SUM(C11:C13) | D14: =SUM(D11:D13) | E14: =SUM(E11:E13) | F14: =SUM(F11:F13) | G14: =SUM(G11:G13)
A15: Senior Debt
A16: Mezzanine Debt
A17: Total Liabilities | B17: =B14+B15+B16 | C17: =C14+C15+C16 | D17: =D14+D15+D16 | E17: =E14+E15+E16 | F17: =F14+F15+F16 | G17: =G14+G15+G16
A18: Common Equity
A19: Retained Earnings | B19: ='Income Statement'!B12 | C19: =B19+'Income Statement'!C12 | D19: =C19+'Income Statement'!D12 | E19: =D19+'Income Statement'!E12 | F19: =E19+'Income Statement'!F12 | G19: =F19+'Income Statement'!G12
A20: Total Equity | B20: =B18+B19 | C20: =C18+C19 | D20: =D18+D19 | E20: =E18+E19 | F20: =F18+F19 | G20: =G18+G19
A21: Total Liabilities & Equity | B21: =B17+B20 | C21: =C17+C20 | D21: =D17+D20 | E21: =E17+E20 | F21: =F17+F20 | G21: =G17+G20

Sheet Cash Flow
A1: Line Item | B1: FY2020 | C1: FY2021 | D1: FY2022 | E1: FY2023 | F1: FY2024 | G1: FY2025
A2: Net Income | B2: ='Income Statement'!B12 | C2: ='Income Statement'!C12 | D2: ='Income Statement'!D12 | E2: ='Income Statement'!E12 | F2: ='Income Statement'!F12 | G2: ='Income Statement'!G12
A3: D&A | B3: ='Income Statement'!B7 | C3: ='Income Statement'!C7 | D3: ='Income Statement'!D7 | E3: ='Income Statement'!E7 | F3: ='Income Statement'!F7 | G3: ='Income Statement'!G7
A4: Changes in Working Capital
A5: Operating CF | B5: =B2+B3+B4 | C5: =C2+C3+C4 | D5: =D2+D3+D4 | E5: =E2+E3+E4 | F5: =F2+F3+F4 | G5: =G2+G3+G4
A6: CapEx
A7: Investing CF | B7: =-B6 | C7: =-C6 | D7: =-D6 | E7: =-E6 | F7: =-F6 | G7: =-G6
A8: Debt Drawdowns
A9: Debt Repayments
A10: Dividends
A11: Financing CF | B11: =B8-B9-B10 | C11: =C8-C9-C10 | D11: =D8-D9-D10 | E11: =E8-E9-E10 | F11: =F8-F9-F10 | G11: =G8-G9-G10
A12: Net Change in Cash | B12: =B5+B7+B11 | C12: =C5+C7+C11 | D12: =D5+D7+D11 | E12: =E5+E7+E11 | F12: =F5+F7+F11 | G12: =G5+G7+G11
A13: Beginning Cash | B13: 0 | C13: =B14 | D13: =C14 | E13: =D14 | F13: =E14 | G13: =F14
A14: Ending Cash | B14: =B12+B13 | C14: =C12+C13 | D14: =D12+D13 | E14: =E12+E13 | F14: =F12+F13 | G14: =G12+G13

Sheet Debt Schedule
A1: Line Item | B1: FY2020 | C1: FY2021 | D1: FY2022 | E1: FY2023 | F1: FY2024 | G1: FY2025
A2: Senior Debt
A3: Beginning Balance | C3: =B6 | D3: =C6 | E3: =D6 | F3: =E6 | G3: =F6
A4: Drawdowns
A5: Repayments
A6: Ending Balance | B6: =B3+B4-B5 | C6: =C3+C4-C5 | D6: =D3+D4-D5 | E6: =E3+E4-E5 | F6: =F3+F4-F5 | G6: =G3+G4-G5
A7: Interest Rate
A8: Interest Expense | B8: =B3*B7 | C8: =C3*C7 | D8: =D3*D7 | E8: =E3*E7 | F8: =F3*F7 | G8: =G3*G7
A9: Mezzanine Debt
A10: Beginning Balance | C10: =B13 | D10: =C13 | E10: =D13 | F10: =E13 | G10: =F13
A11: Drawdowns
A12: Repayments
A13: Ending Balance | B13: =B10+B11-B12 | C13: =C10+C11-C12 | D13: =D10+D11-D12 | E13: =E10+E11-E12 | F13: =F10+F11-F12 | G13: =G10+G11-G12
A14: Interest Rate
A15: Interest Expense | B15: =B10*B14 | C15: =C10*C14 | D15: =D10*D14 | E15: =E10*E14 | F15: =F10*F14 | G15: =G10*G14
A16: Total Interest Expense | B16: =B8+B15 | C16: =C8+C15 | D16: =D8+D15 | E16: =E8+E15 | F16: =F8+F15 | G16: =G8+G15
A17: Total Ending Debt | B17: =B6+B13 | C17: =C6+C13 | D17: =D6+D13 | E17: =E6+E13 | F17: =F6+F13 | G17: =G6+G13

Sheet Returns Analysis
A1: Metric | B1: Value
A2: Entry EV
A3: Exit Multiple
A4: Exit EV | B4: ='Income Statement'!G6*B3
A5: Net Debt at Exit | B5: ='Debt Schedule'!G17
A6: Exit Equity | B6: =B4-B5
A7: Equity Invested
A8: MOIC | B8: =B6/B7
A9: IRR
