Workbook

Sheet Income Statement
A1: LBO Model — Income Statement ($mm)
A2: Line Item | B2: FY2020 | C2: FY2021 | D2: FY2022 | E2: FY2023 | F2: FY2024 | G2: FY2025
A4: Revenue
A5: Cost of Goods Sold
A6: Gross Profit | B6: =B4-B5 | C6: =C4-C5 | D6: =D4-D5 | E6: =E4-E5 | F6: =F4-F5 | G6: =G4-G5
A7: Gross Margin % | B7: =IFERROR(B6/B4,0) | C7: =IFERROR(C6/C4,0) | D7: =IFERROR(D6/D4,0) | E7: =IFERROR(E6/E4,0) | F7: =IFERROR(F6/F4,0) | G7: =IFERROR(G6/G4,0)
A9: Selling, General & Administrative
A10: Research & Development
A11: Other Operating Expenses
A12: Total Operating Expenses | B12: =B9+B10+B11 | C12: =C9+C10+C11 | D12: =D9+D10+D11 | E12: =E9+E10+E11 | F12: =F9+F10+F11 | G12: =G9+G10+G11
A14: EBITDA | B14: =B6-B12 | C14: =C6-C12 | D14: =D6-D12 | E14: =E6-E12 | F14: =F6-F12 | G14: =G6-G12
A15: EBITDA Margin % | B15: =IFERROR(B14/B4,0) | C15: =IFERROR(C14/C4,0) | D15: =IFERROR(D14/D4,0) | E15: =IFERROR(E14/E4,0) | F15: =IFERROR(F14/F4,0) | G15: =IFERROR(G14/G4,0)
A17: Depreciation & Amortization
A18: EBIT (Operating Income) | B18: =B14-B17 | C18: =C14-C17 | D18: =D14-D17 | E18: =E14-E17 | F18: =F14-F17 | G18: =G14-G17
A19: EBIT Margin % | B19: =IFERROR(B18/B4,0) | C19: =IFERROR(C18/C4,0) | D19: =IFERROR(D18/D4,0) | E19: =IFERROR(E18/E4,0) | F19: =IFERROR(F18/F4,0) | G19: =IFERROR(G18/G4,0)
A21: Interest Expense — Senior Debt | B21: ='Debt Schedule'!B13 | C21: ='Debt Schedule'!C13 | D21: ='Debt Schedule'!D13 | E21: ='Debt Schedule'!E13 | F21: ='Debt Schedule'!F13 | G21: ='Debt Schedule'!G13
A22: Interest Expense — Mezzanine | B22: ='Debt Schedule'!B24 | C22: ='Debt Schedule'!C24 | D22: ='Debt Schedule'!D24 | E22: ='Debt Schedule'!E24 | F22: ='Debt Schedule'!F24 | G22: ='Debt Schedule'!G24
A23: Total Interest Expense | B23: =B21+B22 | C23: =C21+C22 | D23: =D21+D22 | E23: =E21+E22 | F23: =F21+F22 | G23: =G21+G22
A25: Earnings Before Tax | B25: =B18-B23 | C25: =C18-C23 | D25: =D18-D23 | E25: =E18-E23 | F25: =F18-F23 | G25: =G18-G23
A26: Effective Tax Rate
A27: Income Tax Expense | B27: =MAX(B25*B26,0) | C27: =MAX(C25*C26,0) | D27: =MAX(D25*D26,0) | E27: =MAX(E25*E26,0) | F27: =MAX(F25*F26,0) | G27: =MAX(G25*G26,0)
A29: Net Income | B29: =B25-B27 | C29: =C25-C27 | D29: =D25-D27 | E29: =E25-E27 | F29: =F25-F27 | G29: =G25-G27
A30: Net Margin % | B30: =IFERROR(B29/B4,0) | C30: =IFERROR(C29/C4,0) | D30: =IFERROR(D29/D4,0) | E30: =IFERROR(E29/E4,0) | F30: =IFERROR(F29/F4,0) | G30: =IFERROR(G29/G4,0)
A33: Formatting Guide
A34: Blue text | B34: =Hardcoded input (user fills in)
A35: Black text | B35: =Formula (auto-calculated)
A36: Green text | B36: =Cross-sheet link

Sheet Debt Schedule
A1: LBO Model — Debt Schedule ($mm)
A2: Line Item | B2: FY2020 | C2: FY2021 | D2: FY2022 | E2: FY2023 | F2: FY2024 | G2: FY2025
A4: SENIOR SECURED DEBT
A5: Beginning Balance | C5: ='Debt Schedule'!B9 | D5: ='Debt Schedule'!C9 | E5: ='Debt Schedule'!D9 | F5: ='Debt Schedule'!E9 | G5: ='Debt Schedule'!F9
A6: Add: Drawdowns & Fundings
A7: Less: Scheduled Repayments
A9: Ending Balance | B9: =B5+B6-B7 | C9: =C5+C6-C7 | D9: =D5+D6-D7 | E9: =E5+E6-E7 | F9: =F5+F6-F7 | G9: =G5+G6-G7
A11: Annual Interest Rate (PIK %)
A12: Average Balance | B12: =(B5+B9)/2 | C12: =(C5+C9)/2 | D12: =(D5+D9)/2 | E12: =(E5+E9)/2 | F12: =(F5+F9)/2 | G12: =(G5+G9)/2
A13: Cash Interest Expense | B13: =B12*B11 | C13: =C12*C11 | D13: =D12*D11 | E13: =E12*E11 | F13: =F12*F11 | G13: =G12*G11
A15: MEZZANINE / PIK DEBT
A16: Beginning Balance | C16: ='Debt Schedule'!B20 | D16: ='Debt Schedule'!C20 | E16: ='Debt Schedule'!D20 | F16: ='Debt Schedule'!E20 | G16: ='Debt Schedule'!F20
A17: Add: Drawdowns & Fundings
A18: Less: Scheduled Repayments
A20: Ending Balance | B20: =B16+B17-B18 | C20: =C16+C17-C18 | D20: =D16+D17-D18 | E20: =E16+E17-E18 | F20: =F16+F17-F18 | G20: =G16+G17-G18
A22: Annual Interest Rate (PIK %)
A23: Average Balance | B23: =(B16+B20)/2 | C23: =(C16+C20)/2 | D23: =(D16+D20)/2 | E23: =(E16+E20)/2 | F23: =(F16+F20)/2 | G23: =(G16+G20)/2
A24: Cash Interest Expense | B24: =B23*B22 | C24: =C23*C22 | D24: =D23*D22 | E24: =E23*E22 | F24: =F23*F22 | G24: =G23*G22
A26: TOTAL DEBT SUMMARY
A27: Total Cash Interest Expense | B27: =B13+B24 | C27: =C13+C24 | D27: =D13+D24 | E27: =E13+E24 | F27: =F13+F24 | G27: =G13+G24

Sheet Balance Sheet
A1: LBO Model — Balance Sheet ($mm)
A2: Line Item | B2: FY2020 | C2: FY2021 | D2: FY2022 | E2: FY2023 | F2: FY2024 | G2: FY2025
A4: ASSETS
A5: Cash & Cash Equivalents | B5: ='Cash Flow Statement'!B32 | C5: ='Cash Flow Statement'!C32 | D5: ='Cash Flow Statement'!D32 | E5: ='Cash Flow Statement'!E32 | F5: ='Cash Flow Statement'!F32 | G5: ='Cash Flow Statement'!G32
A6: Accounts Receivable, Net
A7: Inventory
A8: Prepaid Expenses & Other Current
A9: Total Current Assets | B9: =SUM(B5:B8) | C9: =SUM(C5:C8) | D9: =SUM(D5:D8) | E9: =SUM(E5:E8) | F9: =SUM(F5:F8) | G9: =SUM(G5:G8)
A11: Property, Plant & Equipment, Gross
A12: Less: Accumulated Depreciation
A13: PP&E, Net | B13: =B11-B12 | C13: =C11-C12 | D13: =D11-D12 | E13: =E11-E12 | F13: =F11-F12 | G13: =G11-G12
A14: Goodwill
A15: Intangible Assets, Net
A16: Deferred Tax Assets
A17: Other Long-Term Assets
A18: Total Non-Current Assets | B18: =B13+B14+B15+B16+B17 | C18: =C13+C14+C15+C16+C17 | D18: =D13+D14+D15+D16+D17 | E18: =E13+E14+E15+E16+E17 | F18: =F13+F14+F15+F16+F17 | G18: =G13+G14+G15+G16+G17
A20: TOTAL ASSETS | B20: =B9+B18 | C20: =C9+C18 | D20: =D9+D18 | E20: =E9+E18 | F20: =F9+F18 | G20: =G9+G18
A22: LIABILITIES
A23: Accounts Payable
A24: Accrued Liabilities & Compensation
A25: Deferred Revenue
A26: Current Portion of Long-Term Debt | B26: ='Debt Schedule'!B7 | C26: ='Debt Schedule'!C7 | D26: ='Debt Schedule'!D7 | E26: ='Debt Schedule'!E7 | F26: ='Debt Schedule'!F7 | G26: ='Debt Schedule'!G7
A27: Total Current Liabilities | B27: =B23+B24+B25+B26 | C27: =C23+C24+C25+C26 | D27: =D23+D24+D25+D26 | E27: =E23+E24+E25+E26 | F27: =F23+F24+F25+F26 | G27: =G23+G24+G25+G26
A29: Senior Secured Debt (net of current) | B29: ='Debt Schedule'!B9 | C29: ='Debt Schedule'!C9 | D29: ='Debt Schedule'!D9 | E29: ='Debt Schedule'!E9 | F29: ='Debt Schedule'!F9 | G29: ='Debt Schedule'!G9
A30: Mezzanine / PIK Debt | B30: ='Debt Schedule'!B20 | C30: ='Debt Schedule'!C20 | D30: ='Debt Schedule'!D20 | E30: ='Debt Schedule'!E20 | F30: ='Debt Schedule'!F20 | G30: ='Debt Schedule'!G20
A31: Total Long-Term Debt | B31: =B29+B30 | C31: =C29+C30 | D31: =D29+D30 | E31: =E29+E30 | F31: =F29+F30 | G31: =G29+G30
A32: Deferred Tax Liabilities
A33: Other Long-Term Liabilities
A34: Total Non-Current Liabilities | B34: =B31+B32+B33 | C34: =C31+C32+C33 | D34: =D31+D32+D33 | E34: =E31+E32+E33 | F34: =F31+F32+F33 | G34: =G31+G32+G33
A36: TOTAL LIABILITIES | B36: =B27+B34 | C36: =C27+C34 | D36: =D27+D34 | E36: =E27+E34 | F36: =F27+F34 | G36: =G27+G34
A38: SHAREHOLDERS' EQUITY
A39: Common Stock & Additional Paid-In Capital
A40: Retained Earnings / (Accumulated Deficit) | C40: =B40+'Income Statement'!C29 | D40: =C40+'Income Statement'!D29 | E40: =D40+'Income Statement'!E29 | F40: =E40+'Income Statement'!F29 | G40: =F40+'Income Statement'!G29
A41: Accumulated Other Comprehensive Income (Loss)
A42: Total Shareholders' Equity | B42: =B39+B40+B41 | C42: =C39+C40+C41 | D42: =D39+D40+D41 | E42: =E39+E40+E41 | F42: =F39+F40+F41 | G42: =G39+G40+G41
A44: TOTAL LIABILITIES + EQUITY | B44: =B36+B42 | C44: =C36+C42 | D44: =D36+D42 | E44: =E36+E42 | F44: =F36+F42 | G44: =G36+G42
A45: Balance Sheet Check (must = 0) | B45: =B20-B44 | C45: =C20-C44 | D45: =D20-D44 | E45: =E20-E44 | F45: =F20-F44 | G45: =G20-G44

Sheet Cash Flow Statement
A1: LBO Model — Cash Flow Statement ($mm, Indirect Method)
A2: Line Item | B2: FY2020 | C2: FY2021 | D2: FY2022 | E2: FY2023 | F2: FY2024 | G2: FY2025
A4: OPERATING ACTIVITIES
A5: Net Income | B5: ='Income Statement'!B29 | C5: ='Income Statement'!C29 | D5: ='Income Statement'!D29 | E5: ='Income Statement'!E29 | F5: ='Income Statement'!F29 | G5: ='Income Statement'!G29
A6: Add: Depreciation & Amortization | B6: ='Income Statement'!B17 | C6: ='Income Statement'!C17 | D6: ='Income Statement'!D17 | E6: ='Income Statement'!E17 | F6: ='Income Statement'!F17 | G6: ='Income Statement'!G17
A8: Changes in Working Capital
A9: (Increase) / Decrease in Accounts Receivable | B9: =0 | C9: ='Balance Sheet'!B6-'Balance Sheet'!C6 | D9: ='Balance Sheet'!C6-'Balance Sheet'!D6 | E9: ='Balance Sheet'!D6-'Balance Sheet'!E6 | F9: ='Balance Sheet'!E6-'Balance Sheet'!F6 | G9: ='Balance Sheet'!F6-'Balance Sheet'!G6
A10: (Increase) / Decrease in Inventory | B10: =0 | C10: ='Balance Sheet'!B7-'Balance Sheet'!C7 | D10: ='Balance Sheet'!C7-'Balance Sheet'!D7 | E10: ='Balance Sheet'!D7-'Balance Sheet'!E7 | F10: ='Balance Sheet'!E7-'Balance Sheet'!F7 | G10: ='Balance Sheet'!F7-'Balance Sheet'!G7
A11: Increase / (Decrease) in Accounts Payable | B11: =0 | C11: ='Balance Sheet'!C23-'Balance Sheet'!B23 | D11: ='Balance Sheet'!D23-'Balance Sheet'!C23 | E11: ='Balance Sheet'!E23-'Balance Sheet'!D23 | F11: ='Balance Sheet'!F23-'Balance Sheet'!E23 | G11: ='Balance Sheet'!G23-'Balance Sheet'!F23
A12: Increase / (Decrease) in Accrued Liabilities | B12: =0 | C12: ='Balance Sheet'!C24-'Balance Sheet'!B24 | D12: ='Balance Sheet'!D24-'Balance Sheet'!C24 | E12: ='Balance Sheet'!E24-'Balance Sheet'!D24 | F12: ='Balance Sheet'!F24-'Balance Sheet'!E24 | G12: ='Balance Sheet'!G24-'Balance Sheet'!F24
A13: Increase / (Decrease) in Deferred Revenue | B13: =0 | C13: ='Balance Sheet'!C25-'Balance Sheet'!B25 | D13: ='Balance Sheet'!D25-'Balance Sheet'!C25 | E13: ='Balance Sheet'!E25-'Balance Sheet'!D25 | F13: ='Balance Sheet'!F25-'Balance Sheet'!E25 | G13: ='Balance Sheet'!G25-'Balance Sheet'!F25
A14: Net Change in Working Capital | B14: =SUM(B9:B13) | C14: =SUM(C9:C13) | D14: =SUM(D9:D13) | E14: =SUM(E9:E13) | F14: =SUM(F9:F13) | G14: =SUM(G9:G13)
A16: Net Cash from Operating Activities | B16: =B5+B6+B14 | C16: =C5+C6+C14 | D16: =D5+D6+D14 | E16: =E5+E6+E14 | F16: =F5+F6+F14 | G16: =G5+G6+G14
A18: INVESTING ACTIVITIES
A19: Capital Expenditures (Capex)
A20: Acquisitions, Net of Cash Acquired
A21: Other Investing Activities
A22: Net Cash from Investing Activities | B22: =B19+B20+B21 | C22: =C19+C20+C21 | D22: =D19+D20+D21 | E22: =E19+E20+E21 | F22: =F19+F20+F21 | G22: =G19+G20+G21
A24: FINANCING ACTIVITIES
A25: Proceeds from Debt Drawdowns | B25: ='Debt Schedule'!B6+'Debt Schedule'!B17 | C25: ='Debt Schedule'!C6+'Debt Schedule'!C17 | D25: ='Debt Schedule'!D6+'Debt Schedule'!D17 | E25: ='Debt Schedule'!E6+'Debt Schedule'!E17 | F25: ='Debt Schedule'!F6+'Debt Schedule'!F17 | G25: ='Debt Schedule'!G6+'Debt Schedule'!G17
A26: Repayment of Debt | B26: =-('Debt Schedule'!B7+'Debt Schedule'!B18) | C26: =-('Debt Schedule'!C7+'Debt Schedule'!C18) | D26: =-('Debt Schedule'!D7+'Debt Schedule'!D18) | E26: =-('Debt Schedule'!E7+'Debt Schedule'!E18) | F26: =-('Debt Schedule'!F7+'Debt Schedule'!F18) | G26: =-('Debt Schedule'!G7+'Debt Schedule'!G18)
A27: Dividends Paid to Equity Holders
A28: Net Cash from Financing Activities | B28: =B25+B26+B27 | C28: =C25+C26+C27 | D28: =D25+D26+D27 | E28: =E25+E26+E27 | F28: =F25+F26+F27 | G28: =G25+G26+G27
A30: Net Increase / (Decrease) in Cash | B30: =B16+B22+B28 | C30: =C16+C22+C28 | D30: =D16+D22+D28 | E30: =E16+E22+E28 | F30: =F16+F22+F28 | G30: =G16+G22+G28
A31: Cash & Equivalents — Beginning of Period | C31: ='Cash Flow Statement'!B32 | D31: ='Cash Flow Statement'!C32 | E31: ='Cash Flow Statement'!D32 | F31: ='Cash Flow Statement'!E32 | G31: ='Cash Flow Statement'!F32
A32: Cash & Equivalents — End of Period | B32: =B31+B30 | C32: =C31+C30 | D32: =D31+D30 | E32: =E31+E30 | F32: =F31+F30 | G32: =G31+G30

Sheet Returns Analysis
A1: LBO Model — Returns Analysis
A2: Color code: Blue = input | Black = formula | Green = cross-sheet link
A4: TRANSACTION ASSUMPTIONS
A5: Entry Year
A6: Exit Year
A7: Investment Horizon (Years) | B7: =B6-B5
A9: ENTRY ASSUMPTIONS
A10: LTM EBITDA at Entry ($mm)
A11: Entry EV / EBITDA Multiple
A12: Entry Enterprise Value ($mm) | B12: =B10*B11
A13: Net Debt at Entry ($mm)
A14: Entry Equity Value ($mm) | B14: =B12-B13
A15: Management Rollover ($mm)
A16: Sponsor Equity Invested ($mm) | B16: =B14-B15
A18: EXIT ASSUMPTIONS
A19: LTM EBITDA at Exit ($mm)
A20: Exit EV / EBITDA Multiple
A21: Exit Enterprise Value ($mm) | B21: =B19*B20
A22: Net Debt at Exit ($mm)
A23: Exit Equity Value ($mm) | B23: =B21-B22
A24: Total Proceeds to Sponsor ($mm) | B24: =B23
A26: RETURNS SUMMARY
A27: MOIC (Multiple of Invested Capital) | B27: =IFERROR(B24/B16,0)
A28: IRR (Internal Rate of Return) | B28: =B38
A30: IRR CASH FLOW SCHEDULE
A31: Year 0 — Equity Invested (Entry) | B31: =-B16
A32: Year 1 — Interim Free Cash Flow
A33: Year 2 — Interim Free Cash Flow
A34: Year 3 — Interim Free Cash Flow
A35: Year 4 — Interim Free Cash Flow
A36: Year 5 — Exit Proceeds to Sponsor | B36: =B24
A38: IRR (Computed via IRR Function) | B38: =IFERROR(IRR(B31:B36),0)
