Workbook

Sheet Income Statement
A1: Line Item | B1: FY2020 | C1: FY2021 | D1: FY2022 | E1: FY2023 | F1: FY2024 | G1: FY2025
A2: Revenue
A3: COGS
A4: Gross Profit | B4: =B2-B3 | C4: =C2-C3 | D4: =D2-D3 | E4: =E2-E3 | F4: =F2-F3 | G4: =G2-G3
A5: SG&A
A6: EBITDA | B6: =B4-B5 | C6: =C4-C5 | D6: =D4-D5 | E6: =E4-E5 | F6: =F4-F5 | G6: =G4-G5
A7: D&A
A8: EBIT | B8: =B6-B7 | C8: =C6-C7 | D8: =D6-D7 | E8: =E6-E7 | F8: =F6-F7 | G8: =G6-G7
A9: Interest Expense
A10: EBT | B10: =B8-B9 | C10: =C8-C9 | D10: =D8-D9 | E10: =E8-E9 | F10: =F8-F9 | G10: =G8-G9
A11: Tax
A12: Net Income | B12: =B10-B11 | C12: =C10-C11 | D12: =D10-D11 | E12: =E10-E11 | F12: =F10-F11 | G12: =G10-G11

Sheet Balance Sheet
A1: Line Item | B1: FY2020 | C1: FY2021 | D1: FY2022 | E1: FY2023 | F1: FY2024 | G1: FY2025
A2: Cash
A3: Accounts Receivable
A4: Inventory
A5: Total Current Assets | B5: =SUM(B2:B4) | C5: =SUM(C2:C4) | D5: =SUM(D2:D4) | E5: =SUM(E2:E4) | F5: =SUM(F2:F4) | G5: =SUM(G2:G4)
A6: PP&E Net
A7: Total Assets | B7: =B5+B6 | C7: =C5+C6 | D7: =D5+D6 | E7: =E5+E6 | F7: =F5+F6 | G7: =G5+G6
A8: Accounts Payable
A9: Accrued Expenses
A10: Debt
A11: Total Liabilities | B11: =SUM(B8:B10) | C11: =SUM(C8:C10) | D11: =SUM(D8:D10) | E11: =SUM(E8:E10) | F11: =SUM(F8:F10) | G11: =SUM(G8:G10)
A12: Common Equity
A13: Retained Earnings | B13: ='Income Statement'!B12 | C13: =B13+'Income Statement'!C12 | D13: =C13+'Income Statement'!D12 | E13: =D13+'Income Statement'!E12 | F13: =E13+'Income Statement'!F12 | G13: =F13+'Income Statement'!G12
A14: Total Equity | B14: =B12+B13 | C14: =C12+C13 | D14: =D12+D13 | E14: =E12+E13 | F14: =F12+F13 | G14: =G12+G13
A15: Total Liabilities & Equity | B15: =B11+B14 | C15: =C11+C14 | D15: =D11+D14 | E15: =E11+E14 | F15: =F11+F14 | G15: =G11+G14

Sheet Cash Flow
A1: Line Item | B1: FY2020 | C1: FY2021 | D1: FY2022 | E1: FY2023 | F1: FY2024 | G1: FY2025
A2: Net Income | B2: ='Income Statement'!B12 | C2: ='Income Statement'!C12 | D2: ='Income Statement'!D12 | E2: ='Income Statement'!E12 | F2: ='Income Statement'!F12 | G2: ='Income Statement'!G12
A3: D&A | B3: ='Income Statement'!B7 | C3: ='Income Statement'!C7 | D3: ='Income Statement'!D7 | E3: ='Income Statement'!E7 | F3: ='Income Statement'!F7 | G3: ='Income Statement'!G7
A4: Changes in Working Capital
A5: Operating CF | B5: =B2+B3+B4 | C5: =C2+C3+C4 | D5: =D2+D3+D4 | E5: =E2+E3+E4 | F5: =F2+F3+F4 | G5: =G2+G3+G4
A6: CapEx
A7: Investing CF | B7: =-B6 | C7: =-C6 | D7: =-D6 | E7: =-E6 | F7: =-F6 | G7: =-G6
A8: Net Change in Cash | B8: =B5+B7 | C8: =C5+C7 | D8: =D5+D7 | E8: =E5+E7 | F8: =F5+F7 | G8: =G5+G7
A9: Beginning Cash | B9: 0 | C9: =B10 | D9: =C10 | E9: =D10 | F9: =E10 | G9: =F10
A10: Ending Cash | B10: =B8+B9 | C10: =C8+C9 | D10: =D8+D9 | E10: =E8+E9 | F10: =F8+F9 | G10: =G8+G9
